metabypasscaptcha/__init__.py
metabypasscaptcha/main.py
metabypasscaptcha-0.1.4.dist-info/METADATA
metabypasscaptcha-0.1.4.dist-info/WHEEL
metabypasscaptcha-0.1.4.dist-info/top_level.txt
metabypasscaptcha-0.1.4.dist-info/RECORD
