Metadata-Version: 2.1
Name: metabypasscaptcha
Version: 0.1.4
Author: MetaBypass
Author-email: support@metabypass.tech
Requires-Dist: requests
